oarepo_loose_validation/__init__.py
oarepo_loose_validation/components.py
oarepo_loose_validation/errors.py
oarepo_loose_validation/model.py
oarepo_loose_validation/schema.py
oarepo_loose_validation/version.py
oarepo_loose_validation-0.0.6.dist-info/AUTHORS.rst
oarepo_loose_validation-0.0.6.dist-info/LICENSE
oarepo_loose_validation-0.0.6.dist-info/METADATA
oarepo_loose_validation-0.0.6.dist-info/WHEEL
oarepo_loose_validation-0.0.6.dist-info/top_level.txt
oarepo_loose_validation-0.0.6.dist-info/RECORD
