Metadata-Version: 2.1
Name: oarepo-loose-validation
Version: 0.0.6
Summary: OArepo module that adds support for loose validation
Home-page: https://github.com/oarepo/oarepo-loose-validation
Author: Alžběta Pokorná
Author-email: lili3@cesnet.cz
License: MIT
Keywords: invenio oarepo loose validation
Platform: any
Classifier: Environment :: Web Environment
Classifier: Intended Audience :: Developers
Classifier: License :: OSI Approved :: MIT License
Classifier: Operating System :: OS Independent
Classifier: Programming Language :: Python
Classifier: Topic :: Internet :: WWW/HTTP :: Dynamic Content
Classifier: Topic :: Software Development :: Libraries :: Python Modules
Classifier: Programming Language :: Python :: 3
Classifier: Programming Language :: Python :: 3.6
Classifier: Programming Language :: Python :: 3.7
Classifier: Programming Language :: Python :: 3.8
Classifier: Programming Language :: Python :: 3.9
Classifier: Development Status :: 1 - Planning
License-File: LICENSE
License-File: AUTHORS.rst
Requires-Dist: deepmerge
Provides-Extra: all
Requires-Dist: oarepo[tests] (~=3.3.134) ; extra == 'all'
Requires-Dist: pydocstyle ; extra == 'all'
Requires-Dist: isort ; extra == 'all'
Requires-Dist: oarepo-model-builder ; extra == 'all'
Provides-Extra: build
Requires-Dist: oarepo-model-builder ; extra == 'build'
Provides-Extra: tests
Requires-Dist: oarepo[tests] (~=3.3.134) ; extra == 'tests'
Requires-Dist: pydocstyle ; extra == 'tests'
Requires-Dist: isort ; extra == 'tests'
